pepperize_cdk_github/__init__.py
pepperize_cdk_github/py.typed
pepperize_cdk_github/_jsii/__init__.py
pepperize_cdk_github/_jsii/cdk-github@0.0.1007.jsii.tgz
pepperize_cdk_github-0.0.1007.dist-info/LICENSE
pepperize_cdk_github-0.0.1007.dist-info/METADATA
pepperize_cdk_github-0.0.1007.dist-info/WHEEL
pepperize_cdk_github-0.0.1007.dist-info/top_level.txt
pepperize_cdk_github-0.0.1007.dist-info/RECORD
